ahocorasick.cpython-310-x86_64-linux-gnu.so
pyahocorasick-2.2.0.dist-info/WHEEL
pyahocorasick-2.2.0.dist-info/top_level.txt
pyahocorasick-2.2.0.dist-info/RECORD
pyahocorasick-2.2.0.dist-info/LICENSE
pyahocorasick-2.2.0.dist-info/METADATA
